README.md
setup.py
musicquery/__init__.py
musicquery/musicquery.py
musicquery.egg-info/PKG-INFO
musicquery.egg-info/SOURCES.txt
musicquery.egg-info/dependency_links.txt
musicquery.egg-info/not-zip-safe
musicquery.egg-info/requires.txt
musicquery.egg-info/top_level.txt