Metadata-Version: 1.0
Name: musicquery
Version: 0.24
Summary: Get song_path from matched arguments with song tags
Home-page: http://github.com/prdpx7/musicquery
Author: Pradeep Khileri
Author-email: pradeepchoudhary009@gmail.com
License: MIT
Keywords: music song-tags metadata linux script cli-tool
Platform: UNKNOWN
